CONTRIBUTING.md
MANIFEST.in
README.rst
setup.py
docs/HISTORY.txt
docs/LICENSE.GPL
docs/LICENSE.txt
eea/__init__.py
eea.aliases.egg-info/PKG-INFO
eea.aliases.egg-info/SOURCES.txt
eea.aliases.egg-info/dependency_links.txt
eea.aliases.egg-info/entry_points.txt
eea.aliases.egg-info/namespace_packages.txt
eea.aliases.egg-info/not-zip-safe
eea.aliases.egg-info/requires.txt
eea.aliases.egg-info/top_level.txt
eea/aliases/__init__.py
eea/aliases/configure.zcml
eea/aliases/version.txt