Metadata-Version: 2.1
Name: eea.aliases
Version: 1.4
Summary: zodbupdate aliases
Home-page: https://github.com/eea/eea.aliases
Author: European Environment Agency: IDM2 A-Team
Author-email: eea-edw-a-team-alerts@googlegroups.com
License: GPL
Download-URL: https://pypi.python.org/pypi/eea.aliases
Keywords: EEA Aliases zodbverify zodbupdate
Platform: UNKNOWN
Classifier: Framework :: Plone :: 4.0
Classifier: Framework :: Plone :: 4.1
Classifier: Framework :: Plone :: 4.2
Classifier: Framework :: Plone :: 4.3
Classifier: Framework :: Plone :: 5.1
Classifier: Framework :: Plone :: 5.2
Classifier: Framework :: Plone :: Addon
Classifier: Framework :: Zope :: 2
Classifier: Framework :: Zope :: 4
Classifier: Framework :: Zope
Classifier: Programming Language :: Python :: 2.7
Classifier: Programming Language :: Python :: 3.6
Classifier: Programming Language :: Python :: 3.7
Classifier: Programming Language :: Python
Classifier: Topic :: Software Development :: Libraries :: Python Modules
Classifier: License :: OSI Approved :: GNU General Public License (GPL)
Provides-Extra: test
